[
  {
    "priority": "1",
    "label": "Dashboard",
    "localizer": "Nav_Dashboard",
    "name": "dashboard-page",
    "icon": "fa-light fa-gauge fa-fw",
    "url": "/"
  },
  {
    "priority": "2",
    "label": "Product",
    "localizer": "Nav_Product",
    "name": "product-page",
    "icon": "fa-light fa-cube fa-fw",
    "items": [
      {
        "label": "Product List",
        "localizer": "Nav_Product_List",
        "name": "product-page/productlist-page",
        "url": "/product/list"
      },
      {
        "label": "Product Register",
        "localizer": "Nav_Product_Register",
        "name": "product-page/productregister-page",
        "url": "/product/register"
      }
    ]
  },
  {
    "priority": "3",
    "label": "Schedule",
    "localizer": "Nav_Schedule",
    "name": "schedule-page",
    "icon": "fa-light fa-calendar-days fa-fw",
    "items": [
      {
        "label": "Schedule List",
        "localizer": "Nav_Schedule_ScheduleList",
        "name": "schedule-list-page",
        "url": "#"
      },
      {
        "label": "Schedule Settings",
        "localizer": "Nav_Schedule_ScheduleSetting",
        "name": "schedule-setting-page",
        "url": "#"
      }
    ]
  },
  {
    "priority": "4",
    "label": "User",
    "localizer": "Nav_User",
    "name": "user-page",
    "icon": "fa-light fa-user fa-fw",
    "items": [
      {
        "label": "User List",
        "localizer": "Nav_User_List",
        "name": "user-page/user-list-page",
        "url": "/user/list"
      },
      {
        "label": "User Role",
        "localizer": "Nav_User_Role",
        "name": "user-page/user-role-page",
        "url": "user/role"
      }
    ]
  },
  {
    "priority": "5",
    "label": "System",
    "localizer": "Nav_System",
    "name": "system-page",
    "icon": "fa-light fa-gear fa-fw",
    "url": "#"
  }
]